my_test_ify/__init__.py
my_test_ify/assertive.py
my_test_ify/exceptions.py
my_test_ify/my_test_ify.py
my_test_ify/utils.py
my_test_ify-0.0.2.dist-info/LICENSE
my_test_ify-0.0.2.dist-info/METADATA
my_test_ify-0.0.2.dist-info/WHEEL
my_test_ify-0.0.2.dist-info/top_level.txt
my_test_ify-0.0.2.dist-info/RECORD
