Metadata-Version: 2.1
Name: my-test-ify
Version: 0.0.2
Summary: Micro framework de testes unitários minimalista
Home-page: https://github.com/andrebg28/my-test-ify.git
Author: Andre Luiz
Author-email: andrebg28@gmail.com
Classifier: Programming Language :: Python :: 3
Classifier: License :: OSI Approved :: MIT License
Classifier: Operating System :: OS Independent
Requires-Python: >=3.12
License-File: LICENSE
